daktronics/__init__.py
daktronics/console.py
daktronics/processors/__init__.py
daktronics/processors/base.py
daktronics/processors/water_polo.py
daktronics-1.1.0.dist-info/METADATA
daktronics-1.1.0.dist-info/WHEEL
daktronics-1.1.0.dist-info/top_level.txt
daktronics-1.1.0.dist-info/RECORD
