Metadata-Version: 2.4
Name: daktronics
Version: 1.1.0
Summary: A Python library for reading data from Daktronics consoles.
Author-email: plun1331 <plun1331@gmail.com>
License-Expression: BSD-3-Clause
Project-URL: Homepage, https://github.com/plun1331/Daktronics/
Project-URL: Repository, https://github.com/plun1331/Daktronics/
Project-URL: Bug Tracker, https://github.com/plun1331/Daktronics/issues
Project-URL: Changelog, https://github.com/plun1331/Daktronics/tree/main/CHANGELOG.md
Keywords: console,daktronics,scoreboard,serial
Classifier: Development Status :: 5 - Production/Stable
Classifier: Programming Language :: Python
Requires-Python: >=3.13
Requires-Dist: pyserial~=3.5
